{
  "_meta": {
    "description": "구단별 공식 예매 오픈 규칙(일반예매 기준). 확인된 규칙만 입력하고, 미확인은 비워둡니다.",
    "timezone": "Asia/Seoul",
    "source_policy": "official club ticket policy/posts"
  },
  "안양": {
    "general_sale": {
      "days_before": 4,
      "time": "14:00",
      "source": "FC안양 2026 홈경기 공식 공지 기준"
    },
    "presale": {
      "days_before": 5,
      "time": "14:00"
    }
  },
  "서울": {
    "general_sale": {
      "days_before": 5,
      "time": "18:00",
      "source": "https://www.fcseoul.com/tickets/reserveSingleTicket (홈경기일 기준 5일전 18시)"
    },
    "presale": {
      "days_before": 5,
      "time": "15:00",
      "source": "https://www.fcseoul.com/tickets/reserveSingleTicket (선예매자 15시)"
    }
  },
  "울산": {},
  "전북": {},
  "강원": {},
  "부천": {
    "general_sale": {
      "days_before": 4,
      "time": "14:00",
      "source": "https://bfc1995.com/media/clubNews/81 (2026시즌 홈경기 일반 예매: 경기일 4일 전 14시)"
    },
    "presale": {
      "days_before": 5,
      "time": "14:00",
      "source": "https://bfc1995.com/media/clubNews/81 (2026시즌 홈경기 선예매: 경기일 5일 전 14시)"
    }
  },
  "포항": {},
  "제주": {},
  "인천": {},
  "김천": {},
  "대전": {
    "general_sale": {
      "days_before": 5,
      "time": "13:00",
      "source": "https://www.dhcfc.kr/images/sub/ticket_260223.jpg (일반티켓 예매: 홈경기일 기준 5일 전 13시 오픈)"
    }
  },
  "광주": {}
}
